ADDER/half_adder.v
module half_adder(S,C,A,B);

input A,B;
output S,C;

xor comp1(S,A,B);
and comp2(C,A,B);

endmodule

ADDER/full_adder.v
`include "../ADDER/half_adder.v"
module full_adder (S,C,A,B,Cin);

input A,B,Cin;
output S,C;
wire S1,C1,X;

half_adder comp1(.A(A),.B(B),.S(S1),.C(C1));
half_adder comp2(.A(Cin),.B(S1),.S(S),.C(X));
or comp3(C,X,C1);

endmodule

ADDER/full_adder_tb.v
module full_adder_tb;

reg A,B,Cin;
wire Sum,Carry;
integer i,k;

full_adder full_add(.A(A),.B(B),.Cin(Cin),.S(Sum),.C(Carry));

initial
	begin
		$monitor("time =%0t \t A =%b, B =%b, Cin =%b and Sum =%b, Carry =%b",$time,A,B,Cin,Sum,Carry);
        $dumpfile("full_adder_tb.vcd");
        $dumpvars(0,full_adder_tb);
		
		A = 0;
		B = 0;
		Cin = 0;
	end

initial begin
	for (i = 1; i <= 8; i = i + 1)
		begin
			#10
			k = i;
			
			A = k % 2;
			k = k / 2;
			
			B = k % 2;
			k = k / 2;
			
			Cin = k % 2;
		end
end
//always @(Sum,Carry)
//	$display("time =%0t \t A =%b, B =%b, Cin =%b and Sum =%b, Carry =%b",$time,A,B,Cin,Sum,Carry);

endmodule

ADDER/full_adder_tb.vcd
$date
	Sun Jan 22 01:29:13 2023
$end
$version
	Icarus Verilog
$end
$timescale
	1s
$end
$scope module full_adder_tb $end
$var wire 1 ! Sum $end
$var wire 1 " Carry $end
$var reg 1 # A $end
$var reg 1 $ B $end
$var reg 1 % Cin $end
$var integer 32 & i [31:0] $end
$var integer 32 ' k [31:0] $end
$scope module full_add $end
$var wire 1 # A $end
$var wire 1 $ B $end
$var wire 1 " C $end
$var wire 1 % Cin $end
$var wire 1 ( X $end
$var wire 1 ) S1 $end
$var wire 1 ! S $end
$var wire 1 * C1 $end
$scope module comp1 $end
$var wire 1 # A $end
$var wire 1 $ B $end
$var wire 1 * C $end
$var wire 1 ) S $end
$upscope $end
$scope module comp2 $end
$var wire 1 % A $end
$var wire 1 ) B $end
$var wire 1 ( C $end
$var wire 1 ! S $end
$upscope $end
$upscope $end
$upscope $end
$enddefinitions $end
$comment Show the parameter values. $end
$dumpall
$end
#0
$dumpvars
0*
0)
0(
bx '
b1 &
0%
0$
0#
0"
0!
$end
#10
1!
1)
b10 &
1#
b0 '
#20
b11 &
1$
0#
b0 '
#30
0!
1"
0)
1*
b100 &
1#
b0 '
#40
0"
1!
0*
b101 &
1%
0$
0#
b1 '
#50
1"
0!
1(
1)
b110 &
1#
b1 '
#60
b111 &
1$
0#
b1 '
#70
1!
0(
0)
1*
b1000 &
1#
b1 '
#80
0"
0!
0*
b1001 &
0%
0$
0#
b10 '
